mySelfSum.py
mySelfSum-1.1.dist-info/METADATA
mySelfSum-1.1.dist-info/WHEEL
mySelfSum-1.1.dist-info/top_level.txt
mySelfSum-1.1.dist-info/RECORD
