Metadata-Version: 2.1
Name: mySelfSum
Version: 1.1
Summary: A  module for test
Home-page: https://github.com/vfrtgb158/email
Author: Squidward
Author-email: vzhyu@foxmail.com
License: MIT
Platform: UNKNOWN
